<?xml version="1.0" encoding="utf-8" ?>
<dwsync>
<file name="_bordered-pulled.scss" server="10.80.32.224" local="130917004149326944" remote="130916937600000000" Dst="0" />
<file name="_core.scss" server="10.80.32.224" local="130917004149336944" remote="130916937600000000" Dst="0" />
<file name="_fixed-width.scss" server="10.80.32.224" local="130917004149486953" remote="130916937600000000" Dst="0" />
<file name="_larger.scss" server="10.80.32.224" local="130917004149536956" remote="130916937600000000" Dst="0" />
<file name="_list.scss" server="10.80.32.224" local="130917004149546956" remote="130916937600000000" Dst="0" />
<file name="_icons.scss" server="10.80.32.224" local="130917004149556957" remote="130916937600000000" Dst="0" />
<file name="_mixins.scss" server="10.80.32.224" local="130917004149576958" remote="130916937600000000" Dst="0" />
<file name="_path.scss" server="10.80.32.224" local="130917004149596959" remote="130916937600000000" Dst="0" />
<file name="_rotated-flipped.scss" server="10.80.32.224" local="130917004149606960" remote="130916937600000000" Dst="0" />
<file name="_spinning.scss" server="10.80.32.224" local="130917004149626961" remote="130916937600000000" Dst="0" />
<file name="_stacked.scss" server="10.80.32.224" local="130917004149656963" remote="130916937600000000" Dst="0" />
<file name="_variables.scss" server="10.80.32.224" local="130917004149696965" remote="130916937600000000" Dst="0" />
<file name="font-awesome.scss" server="10.80.32.224" local="130917004149696965" remote="130916937600000000" Dst="0" />
</dwsync>